invenio_imoox/__init__.py
invenio_imoox/cli.py
invenio_imoox/config.py
invenio_imoox/ext.py
invenio_imoox/jobs.py
invenio_imoox/proxies.py
invenio_imoox/records.py
invenio_imoox/services.py
invenio_imoox/tasks.py
invenio_imoox-0.4.1.dist-info/licenses/AUTHORS.rst
invenio_imoox-0.4.1.dist-info/licenses/LICENSE
invenio_imoox-0.4.1.dist-info/METADATA
invenio_imoox-0.4.1.dist-info/WHEEL
invenio_imoox-0.4.1.dist-info/entry_points.txt
invenio_imoox-0.4.1.dist-info/top_level.txt
invenio_imoox-0.4.1.dist-info/RECORD
