Metadata-Version: 2.4
Name: invenio-imoox
Version: 0.4.1
Summary: "Provides API for iMooX."
Home-page: https://github.com/tu-graz-library/invenio-imoox
Author: Graz University of Technology.
Author-email: info@inveniosoftware.org
License: MIT
Platform: any
Classifier: Programming Language :: Python :: 3.12
Classifier: Programming Language :: Python :: 3.13
Classifier: Development Status :: 5 - Production/Stable
Requires-Python: >=3.8
License-File: LICENSE
License-File: AUTHORS.rst
Requires-Dist: click>=7.0.0
Requires-Dist: invenio-records-lom>=0.1.0
Requires-Dist: invenio-jobs>=3.0.0
Requires-Dist: requests>=2.0.0
Provides-Extra: tests
Requires-Dist: invenio-app>=2.0.0; extra == "tests"
Requires-Dist: invenio-cache>=1.1.0; extra == "tests"
Requires-Dist: invenio-search[opensearch2]>=2.1.0; extra == "tests"
Requires-Dist: pytest-invenio>=1.4.3; extra == "tests"
Requires-Dist: pytest-black-ng>=0.4.0; extra == "tests"
Requires-Dist: ruff>=0.4.4; extra == "tests"
Requires-Dist: Sphinx>=4.4.0; extra == "tests"
Dynamic: license-file
